{
    "• Região": "Sudeste",
    "• Estados limítrofes": "Espírito Santo (nordeste), Minas Gerais (noroeste) e São Paulo (sudoeste)",
    "• Regiões intermediárias": "5",
    "• Regiões imediatas": "14",
    "• Municípios": "92",
    "Capital": "Rio de Janeiro",
    "• Governador(a)": "Cláudio Castro (PL)",
    "• Vice-governador(a)": "Thiago Pampolha (MDB)",
    "• Deputados federais": "46",
    "• Deputados estaduais": "70",
    "• Senadores": "Carlos Portinho (PL)Flávio Bolsonaro (PL)Romário (PL)",
    "• Área total": "43 750,425 km² (24º) [1]",
    "População": "2021",
    "• Estimativa": "17 463 349 hab. (3º)[2]",
    "• Censo 2022": "16 055 174 hab. (3º)[3]",
    "• Densidade": "366,97 hab./km² (2º)",
    "Economia": "2021[4]",
    "• PIB total": "1.153.512 trilhão (2º)",
    "• PIB per capita": "71.850 (2º)",
    "Indicadores": "2016/2017[5][6]",
    "• Esperança de vida (2017)": "76,5 anos (8º)",
    "• Mortalidade infantil (2017)": "11,1‰ nasc. (20º)",
    "• Alfabetização (2016)": "97,3% (2º)",
    "• IDH (2021)": "0,762 (8º) – alto [7]",
    "Fuso horário": "UTC−3, America/Sao_Paulo",
    "Clima": "tropicaltropical de altitude Aw, Cwa",
    "Cód. ISO 3166-2": "BR-RJ",
    "Website": "http://www.rj.gov.br/"
}