{
    "Outros nomes": [
        "Al Hajj Malik Al-Shabazz",
        "(الحاجّ مالك الشباز)"
    ],
    "Nascimento": "19 de maio de 1925Omaha, Nebraska",
    "Morte": "21 de fevereiro de 1965 (39 anos)Manhattan, Nova Iorque",
    "Nacionalidade": "norte-americano",
    "Parentesco": [
        "Earl Little",
        "Louise Helen Norton Little"
    ],
    "Cônjuge": "Betty Shabazz, 1958",
    "Filho(a)(s)": [
        "Attallah Shabazz",
        "Qubilah Shabazz",
        "Ilyasah Shabazz",
        "Gamilah Lumumba Shabazz",
        "Malikah Shabazz",
        "Malaak Shabazz"
    ],
    "Ocupação": "ativista políticodefensor dos direitos dos negros",
    "Filiação": [
        "Nação do Islã",
        "Muslim Mosque, Inc.",
        "Organização para a Unidade Afro-Americana"
    ],
    "Movimento literário": [
        "Nacionalismo negro",
        "Pan-africanismo"
    ],
    "Ideias notáveis": "Analogia dos dois escravos"
}