{
    "Capital e maior cidade": "Beirute33° 54′ N, 35° 32′ L",
    "Língua oficial": "Árabe[1]",
    "Outras línguas": "Árabe libanês e francês[1]",
    "Gentílico": "libanês(a)",
    "Governo": "República parlamentarista unitária[2]",
    "• Presidente": "Joseph Aoun",
    "• Primeiro-ministro": "Nawaf Salam",
    "• Presidente do Parlamento": "Nabih Berri",
    "• Declarada": "26 de novembro de 1941",
    "• Reconhecida": "22 de novembro de 1943",
    "• Total": "US$ 58 bilhões*[5] (82.º)",
    "• Água (%)": "1,6",
    "Fronteira": "Síria (ao norte e leste) e Israel (ao sul)[3]",
    "• Estimativa para 2018": "6 859 408[4] hab. (109.º)",
    "• Densidade": "560 hab./km² (21.º)",
    "PIB (base PPC )": "Estimativa para 2019",
    "• Per capita": "US$ 9 655[5] (67.º)",
    "IDH (2019)": "0,744 (92.º) – alto[6]",
    "Moeda": "Libra libanesa (LBP)",
    "Fuso horário": "(UTC+2)",
    "• Verão ( DST )": "(UTC+3)",
    "Cód. ISO": "LBN",
    "Cód. Internet": ".lb",
    "Cód. telef.": "+961",
    "Website governamental": [
        "dawlati .gov .lb",
        "dawlati .gov .lb /en /home"
    ]
}